{
  "configVersion": 1,
  "timestamp": 1765890031875,
  "index": "/index.html",
  "assetGroups": [
    {
      "name": "app",
      "installMode": "prefetch",
      "updateMode": "prefetch",
      "cacheQueryOptions": {
        "ignoreVary": true
      },
      "urls": [
        "/index.html",
        "/main-K3JR72KC.js",
        "/manifest.webmanifest",
        "/styles-6QCCZDQN.css"
      ],
      "patterns": []
    },
    {
      "name": "assets",
      "installMode": "lazy",
      "updateMode": "prefetch",
      "cacheQueryOptions": {
        "ignoreVary": true
      },
      "urls": [
        "/icons/la-logo.png"
      ],
      "patterns": []
    }
  ],
  "dataGroups": [],
  "hashTable": {
    "/icons/la-logo.png": "01acc749abcaf0a7e31dcabe57c586eb69340666",
    "/index.html": "3d25d14fe5644446c94d52f7d0c2c2bcad3f26c2",
    "/main-K3JR72KC.js": "d3b3b1c4abb83e48f18ab3bb474a7df7627ec35e",
    "/manifest.webmanifest": "dfc00be345f28b36a4fccb60b2e20b78a28a76e3",
    "/styles-6QCCZDQN.css": "c5e4146c830b95c896ca13ea20046eb7aef66489"
  },
  "navigationUrls": [
    {
      "positive": true,
      "regex": "^\\/.*$"
    },
    {
      "positive": false,
      "regex": "^\\/(?:.+\\/)?[^/]*\\.[^/]*$"
    },
    {
      "positive": false,
      "regex": "^\\/(?:.+\\/)?[^/]*__[^/]*$"
    },
    {
      "positive": false,
      "regex": "^\\/(?:.+\\/)?[^/]*__[^/]*\\/.*$"
    }
  ],
  "navigationRequestStrategy": "performance"
}